keyrings/__init__.py
keyrings/unixpass.py
keyrings.unixpass-0.0.2.dist-info/LICENSE
keyrings.unixpass-0.0.2.dist-info/METADATA
keyrings.unixpass-0.0.2.dist-info/WHEEL
keyrings.unixpass-0.0.2.dist-info/entry_points.txt
keyrings.unixpass-0.0.2.dist-info/top_level.txt
keyrings.unixpass-0.0.2.dist-info/RECORD
