Metadata-Version: 2.1
Name: keyrings.unixpass
Version: 0.0.2
Summary: Keyring plugin for the pass password manager
Author-email: Alessandro Cerruti <whisper@chrooti.org>
License: MIT
Project-URL: Homepage, https://gitlab.com/chrooti/keyrings.unixpass
Keywords: pass,keyring
Classifier: Development Status :: 4 - Beta
Classifier: Intended Audience :: Developers
Classifier: License :: OSI Approved :: MIT License
Classifier: Programming Language :: Python :: 3
Classifier: Programming Language :: Python :: 3 :: Only
Requires-Python: >=3.7
License-File: LICENSE
